README.md
setup.py
src/behavior_eval/__init__.py
src/behavior_eval/agent_eval.py
src/behavior_eval/global_config.yaml
src/behavior_eval/main.py
src/behavior_eval/data/__init__.py
src/behavior_eval/data/demo_names.json
src/behavior_eval/data/demo_stats.json
src/behavior_eval/evaluation/__init__.py
src/behavior_eval/evaluation/action_sequencing/__init__.py
src/behavior_eval/evaluation/action_sequencing/action_sequence_evaluator.py
src/behavior_eval/evaluation/action_sequencing/resources/__init__.py
src/behavior_eval/evaluation/action_sequencing/resources/prompt_templates/__init__.py
src/behavior_eval/evaluation/action_sequencing/resources/prompt_templates/one_shot.py
src/behavior_eval/evaluation/action_sequencing/scripts/__init__.py
src/behavior_eval/evaluation/action_sequencing/scripts/evaluate_results.py
src/behavior_eval/evaluation/action_sequencing/scripts/generate_prompts.py
src/behavior_eval/evaluation/action_sequencing/scripts/replanning.py
src/behavior_eval/evaluation/goal_interpretation/__init__.py
src/behavior_eval/evaluation/goal_interpretation/resources/__init__.py
src/behavior_eval/evaluation/goal_interpretation/resources/data/100_selected_demos.txt
src/behavior_eval/evaluation/goal_interpretation/resources/data/__init__.py
src/behavior_eval/evaluation/goal_interpretation/resources/data/all_conditions.json
src/behavior_eval/evaluation/goal_interpretation/resources/data/all_conditions_sampled.json
src/behavior_eval/evaluation/goal_interpretation/resources/data/all_objects.json
src/behavior_eval/evaluation/goal_interpretation/resources/data/binary_relations_behavior.json
src/behavior_eval/evaluation/goal_interpretation/resources/data/goal_interpretation_prompts.json
src/behavior_eval/evaluation/goal_interpretation/resources/data/instructions_by_activity_name.json
src/behavior_eval/evaluation/goal_interpretation/resources/data/just_objects.json
src/behavior_eval/evaluation/goal_interpretation/resources/data/llm_prompts.json
src/eai_eval.egg-info/PKG-INFO
src/eai_eval.egg-info/SOURCES.txt
src/eai_eval.egg-info/dependency_links.txt
src/eai_eval.egg-info/entry_points.txt
src/eai_eval.egg-info/requires.txt
src/eai_eval.egg-info/top_level.txt
