Metadata-Version: 2.1
Name: eai-eval
Version: 1.0.1
Home-page: https://github.com/embodied-agent-interface/embodied-agent-interface
Author: stanford
Requires-Python: >=3.8
Requires-Dist: lark
Requires-Dist: bddl-eval
Requires-Dist: pyquaternion
Requires-Dist: pddlgym
Requires-Dist: ipdb
Requires-Dist: networkx>=3.1
Requires-Dist: numpy>=1.20.0
Requires-Dist: fire
Requires-Dist: gdown
